Workbook

Sheet README
A1: FIN 325 Capstone Analyst Workbook Template v2
A2: Structured workbook for the final investment committee recommendation.
A4: How to Use This Workbook
A5: 1. Select company | B5: Use the same company from the memo sequence unless your instructor approves a change.
A6: 2. Replace inputs | B6: Blue/yellow cells are student inputs. Replace sample data with company-specific data.
A7: 3. Cite sources | B7: Use the Sources tab for annual reports, market data, peer multiples, and assumptions.
A8: 4. Review formulas | B8: Black text cells are formulas; green cells link across tabs.
A9: 5. Summarize dashboard | B9: Use the Dashboard tab to form a final recommendation and decision logic.
A12: Color Conventions
A13: Blue text / yellow fill | B13: Student input
A14: Black text | B14: Formula or calculation
A15: Green text / teal fill | B15: Linked from another worksheet
A16: Gold fill | B16: Interpretation or professional judgment

Sheet Company Inputs
A1: Company Inputs
A2: Company, market, and financial statement inputs. Units are $mm unless otherwise noted.
G3: README | H3: Inputs | I3: Dashboard | J3: Sources
A4: Company and Market Inputs
A5: Company Name | B5: ExampleCo
A6: Ticker | B6: EXMP
A7: Exchange | B7: NYSE/NASDAQ
A8: Fiscal Year End | B8: 2025
A9: Current Market Price ($/share) | B9: 90
A10: Shares Outstanding (mm) | B10: 100
A11: Market Value of Debt ($mm) | B11: 300
A12: Cash and Equivalents ($mm) | B12: 120
A13: Tax Rate | B13: 0.21
A14: Observation Date | B14: 2026-08-16
A17: Financial Statement Inputs ($mm)
A18: Metric | B18: FY2023 | C18: FY2024 | D18: FY2025
A19: Revenue | B19: 950 | C19: 1040 | D19: 1120
A20: COGS | B20: 520 | C20: 560 | D20: 600
A21: EBITDA | B21: 220 | C21: 255 | D21: 285
A22: EBIT | B22: 180 | C22: 210 | D22: 235
A23: Interest Expense | B23: 18 | C23: 20 | D23: 22
A24: Pretax Income | B24: 162 | C24: 190 | D24: 213
A25: Taxes | B25: 34 | C25: 40 | D25: 45
A26: Net Income | B26: 128 | C26: 150 | D26: 168
A27: Cash | B27: 80 | C27: 100 | D27: 120
A28: Accounts Receivable | B28: 110 | C28: 120 | D28: 130
A29: Inventory | B29: 90 | C29: 96 | D29: 102
A30: Current Assets | B30: 360 | C30: 395 | D30: 430
... A38: Share Repurchases | B38: 20 | C38: 25 | D38: 30

Sheet Financial Health
A1: Financial Health Diagnosis
A2: Liquidity, profitability, efficiency, leverage, and DuPont analysis.
G3: README | H3: Inputs | I3: Dashboard | J3: Sources
A4: Key Financial Ratios
A5: Metric | B5: FY2023 | C5: FY2024 | D5: FY2025 | E5: Interpretation
A6: Revenue Growth | B6: n.m. | C6: ='Company Inputs'!C19/'Company Inputs'!B19-1 | D6: ='Company Inputs'!D19/'Company Inputs'!C19-1 | E6: Growth supports or challenges valuation assumptions.
A7: Gross Margin | B7: =('Company Inputs'!B19-'Company Inputs'!B20)/'Company Inputs'!B19 | C7: =('Company Inputs'!C19-'Company Inputs'!C20)/'Company Inputs'!C19 | D7: =('Company Inputs'!D19-'Company Inputs'!D20)/'Company Inputs'!D19 | E7: Gross profitability before operating costs.
A8: Operating Margin | B8: ='Company Inputs'!B22/'Company Inputs'!B19 | C8: ='Company Inputs'!C22/'Company Inputs'!C19 | D8: ='Company Inputs'!D22/'Company Inputs'!D19 | E8: Operating profit relative to sales.
A9: Net Margin | B9: ='Company Inputs'!B26/'Company Inputs'!B19 | C9: ='Company Inputs'!C26/'Company Inputs'!C19 | D9: ='Company Inputs'!D26/'Company Inputs'!D19 | E9: After-tax profitability.
A10: Current Ratio | B10: ='Company Inputs'!B30/'Company Inputs'!B31 | C10: ='Company Inputs'!C30/'Company Inputs'!C31 | D10: ='Company Inputs'!D30/'Company Inputs'!D31 | E10: Short-term liquidity.
A11: Quick Ratio | B11: =('Company Inputs'!B30-'Company Inputs'!B29)/'Company Inputs'!B31 | C11: =('Company Inputs'!C30-'Company Inputs'!C29)/'Company Inputs'!C31 | D11: =('Company Inputs'!D30-'Company Inputs'!D29)/'Company Inputs'!D31 | E11: Liquidity excluding inventory.
A12: Debt-to-Equity | B12: ='Company Inputs'!B33/'Company Inputs'!B34 | C12: ='Company Inputs'!C33/'Company Inputs'!C34 | D12: ='Company Inputs'!D33/'Company Inputs'!D34 | E12: Financial leverage.
A13: ROA | B13: ='Company Inputs'!B26/'Company Inputs'!B32 | C13: ='Company Inputs'!C26/'Company Inputs'!C32 | D13: ='Company Inputs'!D26/'Company Inputs'!D32 | E13: Return on assets.
A14: ROE | B14: ='Company Inputs'!B26/'Company Inputs'!B34 | C14: ='Company Inputs'!C26/'Company Inputs'!C34 | D14: ='Company Inputs'!D26/'Company Inputs'!D34 | E14: Return on equity.
A15: Asset Turnover | B15: ='Company Inputs'!B19/'Company Inputs'!B32 | C15: ='Company Inputs'!C19/'Company Inputs'!C32 | D15: ='Company Inputs'!D19/'Company Inputs'!D32 | E15: Revenue generated per dollar of assets.
A16: Equity Multiplier | B16: ='Company Inputs'!B32/'Company Inputs'!B34 | C16: ='Company Inputs'!C32/'Company Inputs'!C34 | D16: ='Company Inputs'!D32/'Company Inputs'!D34 | E16: Leverage component of DuPont.
A17: DuPont ROE | B17: =B9*B14*B15 | C17: =C9*C14*C15 | D17: =D9*D14*D15 | E17: Net margin × asset turnover × equity multiplier.
A20: Student Interpretation
A21: Strengths to highlight | B21: [Student completes]
A22: Concerns to monitor | B22: [Student completes]
A23: Memo 1 decision | B23: [Student completes]

Sheet Valuation
A1: Valuation Analysis
A2: DDM, P/E multiple, simple DCF, valuation range, and market-price comparison.
G3: README | H3: Inputs | I3: Dashboard | J3: Sources
A4: Valuation Inputs
A5: Current Market Price ($/share) | B5: ='Company Inputs'!B9
A6: Current Dividend ($/share) | B6: 1.2
A7: Dividend Growth Rate | B7: 0.04
A8: Required Return | B8: ='Risk and Return'!B14
A9: EPS ($/share) | B9: 4.9
A10: Selected P/E Multiple | B10: 18
A11: FCF Year 0 ($mm) | B11: ='Company Inputs'!D35-'Company Inputs'!D36
A12: FCF Growth Rate | B12: 0.05
A13: Terminal Growth Rate | B13: 0.025
A14: Net Debt ($mm) | B14: ='Company Inputs'!B11-'Company Inputs'!B12
A15: Shares Outstanding (mm) | B15: ='Company Inputs'!B10
A18: Valuation Outputs
A19: DDM Value / Share | B19: =B6*(1+B7)/(B8-B7)
A20: P/E Implied Value / Share | B20: =B9*B10
A21: DCF Implied Value / Share | B21: =B40
A22: Low Valuation | B22: =MIN(B19:B21)
A23: Base Valuation | B23: =AVERAGE(B19:B21)
A24: High Valuation | B24: =MAX(B19:B21)
A25: Upside / Downside to Market | B25: =B23/B5-1
A26: Valuation Signal | B26: =IF(B25>0.1,"Potentially Undervalued",IF(B25<-0.1,"Potentially Overvalued","Near Fair Value"))
A29: Simple DCF Forecast
A30: Year | B30: FCF ($mm) | C30: PV Factor | D30: PV of FCF ($mm)
A31: 1 | B31: =$B$11*(1+$B$12)^1 | C31: =1/(1+'WACC'!$B$17)^1 | D31: =B31*C31
A32: 2 | B32: =$B$11*(1+$B$12)^2 | C32: =1/(1+'WACC'!$B$17)^2 | D32: =B32*C32
A33: 3 | B33: =$B$11*(1+$B$12)^3 | C33: =1/(1+'WACC'!$B$17)^3 | D33: =B33*C33
A34: 4 | B34: =$B$11*(1+$B$12)^4 | C34: =1/(1+'WACC'!$B$17)^4 | D34: =B34*C34
A35: 5 | B35: =$B$11*(1+$B$12)^5 | C35: =1/(1+'WACC'!$B$17)^5 | D35: =B35*C35
A36: Terminal Value ($mm) | B36: =B35*(1+$B$13)/('WACC'!$B$17-$B$13)
A37: PV of Terminal Value ($mm) | B37: =B36*C35
A38: Enterprise Value ($mm) | B38: =SUM(D31:D35)+B37
A39: Equity Value ($mm) | B39: =B38-$B$14
A40: DCF Value / Share | B40: =B39/$B$15

Sheet Risk and Return
A1: Risk and Return
A2: Beta, CAPM required return, expected return, and risk signal.
G3: README | H3: Inputs | I3: Dashboard | J3: Sources
A4: Inputs
A5: Risk-Free Rate | B5: 0.04
A6: Expected Market Return | B6: 0.1
A7: Company Beta | B7: 1.2
A8: Expected Stock Return | B8: 0.11
A9: Historical Standard Deviation | B9: 0.24
A10: Benchmark Return | B10: 0.1
A12: Outputs
A13: Equity Risk Premium | B13: =B6-B5
A14: CAPM Required Return | B14: =B5+B7*(B6-B5)
A15: Expected Return Spread | B15: =B8-B14
A16: Risk Signal | B16: =IF(B15>0.02,"Favorable",IF(B15<-0.02,"Unfavorable","Mixed"))

Sheet WACC
A1: Weighted Average Cost of Capital
A2: Cost of equity, cost of debt, weights, and WACC.
G3: README | H3: Inputs | I3: Dashboard | J3: Sources
A4: Inputs and Linked Values
A5: Market Value of Equity ($mm) | B5: ='Company Inputs'!B9*'Company Inputs'!B10
A6: Market Value of Debt ($mm) | B6: ='Company Inputs'!B11
A7: Total Capital ($mm) | B7: =B5+B6
A8: Cost of Equity | B8: ='Risk and Return'!B14
A9: Pre-Tax Cost of Debt | B9: 0.06
A10: Tax Rate | B10: ='Company Inputs'!B13
A13: Outputs
A14: Equity Weight | B14: =B5/B7
A15: Debt Weight | B15: =B6/B7
A16: After-Tax Cost of Debt | B16: =B9*(1-B10)
A17: WACC | B17: =B14*B8+B15*B16

Sheet Capital Allocation
A1: Capital Allocation and Project Discipline
A2: NPV, IRR, payback, and scenario analysis.
G3: README | H3: Inputs | I3: Dashboard | J3: Sources
A4: Project Inputs
A5: Initial Investment ($mm) | B5: -100
A6: Annual Cash Flow - Base ($mm) | B6: 28
A7: Project Life (Years) | B7: 5
A8: Discount Rate / WACC | B8: ='WACC'!B17
A9: Downside Annual CF ($mm) | B9: 22
A10: Upside Annual CF ($mm) | B10: 34
A13: Base Case Cash Flows
A14: Year | B14: Cash Flow ($mm) | C14: Cumulative CF ($mm)
A15: 0 | B15: =$B$5 | C15: =SUM($B$15:B15)
A16: 1 | B16: =$B$6 | C16: =SUM($B$15:B16)
A17: 2 | B17: =$B$6 | C17: =SUM($B$15:B17)
A18: 3 | B18: =$B$6 | C18: =SUM($B$15:B18)
A19: 4 | B19: =$B$6 | C19: =SUM($B$15:B19)
A20: 5 | B20: =$B$6 | C20: =SUM($B$15:B20)
A23: Outputs
A24: NPV ($mm) | B24: =NPV(B8,B16:B20)+B15
A25: IRR | B25: =IRR(B15:B20)
A26: Simple Payback (Years) | B26: =ABS(B5)/B6
A27: Decision Signal | B27: =IF(B24>0,"Positive NPV","Negative NPV")
A31: Scenario Analysis
A32: Scenario | B32: Annual CF ($mm) | C32: NPV ($mm) | D32: Signal
A33: Downside | B33: =B9 | C33: =B33*(1-(1+$B$8)^(-$B$7))/$B$8+$B$5 | D33: =IF(C33>0,"Positive NPV","Negative NPV")
A34: Base | B34: =B6 | C34: =B34*(1-(1+$B$8)^(-$B$7))/$B$8+$B$5 | D34: =IF(C34>0,"Positive NPV","Negative NPV")
A35: Upside | B35: =B10 | C35: =B35*(1-(1+$B$8)^(-$B$7))/$B$8+$B$5 | D35: =IF(C35>0,"Positive NPV","Negative NPV")

Sheet Strategic Finance
A1: Strategic Finance and Stress Testing
A2: Operating leverage, coverage, working capital, payout, and flexibility.
G3: README | H3: Inputs | I3: Dashboard | J3: Sources
A4: Inputs
A5: Price per Unit ($) | B5: 100
A6: Variable Cost per Unit ($) | B6: 60
A7: Fixed Costs ($mm) | B7: 100
A8: Units Sold (mm) | B8: 4
A9: Debt ($mm) | B9: ='Company Inputs'!B11
A10: Interest Rate | B10: 0.07
A11: Annual Sales ($mm) | B11: ='Company Inputs'!D19
A12: Inventory Days | B12: 45
A13: Receivable Days | B13: 35
A14: Payable Days | B14: 30
A15: Dividend Payout Ratio | B15: ='Company Inputs'!D37/'Company Inputs'!D26
A18: Outputs
A19: Contribution Margin / Unit | B19: =B5-B6
A20: EBIT ($mm) | B20: =B19*B8-B7
A21: Break-Even Units (mm) | B21: =B7/B19
A22: Degree of Operating Leverage | B22: =IFERROR((B19*B8)/B20,"")
A23: Annual Interest ($mm) | B23: =B9*B10
A24: Interest Coverage | B24: =IFERROR(B20/B23,"")
A25: Cash Conversion Cycle (Days) | B25: =B12+B13-B14
A26: Approx. Cash Tied in CCC ($mm) | B26: =B11/365*B25
A27: Flexibility Signal | B27: =IF(B24<2,"Coverage Concern",IF(B25>90,"Working Capital Concern","Monitor / Acceptable"))
A31: Student Interpretation
A32: Financial flexibility assessment | B32: [Student completes]
A33: Stewardship / integrity consideration | B33: [Student completes]
A34: Memo 4 decision | B34: [Student completes]

Sheet Dashboard
A1: Investment Committee Dashboard
A2: Complete this page last. It summarizes the final capstone recommendation.
G3: README | H3: Inputs | I3: Dashboard | J3: Sources
A4: Executive Recommendation
A5: Company | B5: ='Company Inputs'!B5
A6: Ticker | B6: ='Company Inputs'!B6
A7: Current Price | B7: ='Company Inputs'!B9
A8: Final Recommendation | B8: Watchlist
A9: One-Sentence Thesis | B9: I recommend [recommendation] because [reason 1], [reason 2], and [reason 3], although [key risk].
A10: Key Risk | B10: [Insert the most important risk or assumption.]
A13: Decision Driver Scorecard
A14: Driver | B14: Metric | C14: Signal | D14: Interpretation
A15: Financial Health | B15: ='Financial Health'!D14 | C15: =IF(B15>0.15,"Favorable",IF(B15<0.08,"Unfavorable","Mixed")) | D15: [Explain financial health evidence]
A16: Valuation | B16: ='Valuation'!B25 | C16: =IF(B16>0.1,"Favorable",IF(B16<-0.1,"Unfavorable","Mixed")) | D16: [Explain valuation evidence]
A17: Risk and Return | B17: ='Risk and Return'!B15 | C17: =IF(B17>0.02,"Favorable",IF(B17<-0.02,"Unfavorable","Mixed")) | D17: [Explain risk-return evidence]
A18: WACC | B18: ='WACC'!B17 | C18: =IF(B18<0.08,"Favorable",IF(B18>0.12,"Unfavorable","Mixed")) | D18: [Explain WACC evidence]
A19: Capital Allocation | B19: ='Capital Allocation'!B24 | C19: =IF(B19>0,"Favorable","Unfavorable") | D19: [Explain capital allocation evidence]
A20: Strategic Finance | B20: ='Strategic Finance'!B24 | C20: =IF(B20>=3,"Favorable",IF(B20<2,"Unfavorable","Mixed")) | D20: [Explain strategic finance evidence]
A24: Final Recommendation Checklist
A25: Requirement | B25: Complete?
A26: Clear recommendation in opening paragraph | B26: No
A27: Company and ticker identified | B27: No
A28: Market price and date included | B28: No
A29: Financial health interpreted | B29: No
A30: Valuation compared with market price | B30: No
A31: Risk and required return discussed | B31: No
A32: WACC interpreted as hurdle rate | B32: No
A33: Capital allocation evidence included | B33: No
A34: Strategic finance and stewardship addressed | B34: No
A35: Risks and limitations explicit | B35: No
A36: Sources documented | B36: No
A40: Dashboard Notes
A41: Use this dashboard to write the executive recommendation.
A42: Do not force a recommendation. If the evidence is mixed, choose Watchlist or Recommend with Caution.
A43: The dashboard is not the final report; it is the evidence map for the final report.

Sheet Sources
A1: Sources
A2: Plain-text source log for data and assumptions.
A4: Source Log
A5: Category | B5: Data Item | C5: Plain-Text URL or Source Name | D5: Date Accessed | E5: Notes
A6: Annual report | B6: Financial statements | C6: Paste annual report / 10-K source here | E6: Use for financial statement inputs.
A7: Market data | B7: Current price | C7: Paste market data source here | E7: Record observation date.
A8: Market data | B8: Beta | C8: Paste beta source here | E8: Record source methodology if available.
A9: Assumption | B9: Risk-free rate | C9: Paste source here | E9: Treasury rate or instructor assumption.
A10: Assumption | B10: Market return | C10: Paste source here | E10: Historical or expected market return.
A11: Peer data | B11: P/E multiple | C11: Paste source here | E11: Document peer set or industry basis.
